omnia_timeseries_sdk/__init__.py
omnia_timeseries_sdk/_config.py
omnia_timeseries_sdk/_utils.py
omnia_timeseries_sdk/client.py
omnia_timeseries_sdk/exceptions.py
omnia_timeseries_sdk/resources.py
omnia_timeseries_sdk/timeseries.py
tests/functional/__init__.py
tests/functional/conftest.py
tests/functional/test_apiclient.py
tests/unit/__init__.py
tests/unit/conftest.py
tests/unit/test_datapoint.py
tests/unit/test_datapoints.py
tests/unit/test_datapointslist.py
tests/unit/test_general.py
tests/unit/test_omniaresource.py
tests/unit/test_omniaresourcelist.py
tests/unit/test_timeseries.py
tests/unit/test_timeserieslist.py
tests/unit/test_utils.py
omnia_timeseries_sdk-0.2.1.dist-info/LICENSE
omnia_timeseries_sdk-0.2.1.dist-info/METADATA
omnia_timeseries_sdk-0.2.1.dist-info/WHEEL
omnia_timeseries_sdk-0.2.1.dist-info/top_level.txt
omnia_timeseries_sdk-0.2.1.dist-info/zip-safe
omnia_timeseries_sdk-0.2.1.dist-info/RECORD
