Metadata-Version: 2.1
Name: omnia-timeseries-sdk
Version: 0.2.1
Summary: Python software developer kit for the Omnia Timeseries API.
Home-page: https://github.com/equinor/omnia-timeseries-sdk-python
Author: Per Voie
License: MIT
Platform: UNKNOWN
Classifier: Development Status :: 2 - Pre-Alpha
Classifier: License :: Other/Proprietary License
Classifier: Programming Language :: Python :: 3
Classifier: Topic :: Scientific/Engineering
Classifier: Topic :: Software Development :: Libraries :: Python Modules
Requires-Python: ~=3.7
Requires-Dist: matplotlib (<4,>=3)
Requires-Dist: adal (<2,>=1)
Requires-Dist: pandas (<1,>=0.25.3)
